trade_cli/__init__.py
trade_cli/cli.py
trade_cli-0.1.21.dist-info/entry_points.txt
trade_cli-0.1.21.dist-info/WHEEL
trade_cli-0.1.21.dist-info/METADATA
trade_cli-0.1.21.dist-info/RECORD
